{
  "DEMO-TU-001": "/vehicle-photos/DEMO-TU-001.jpg",
  "DEMO-TU-002": "/vehicle-photos/DEMO-TU-002.jpg",
  "DEMO-AR-001": "/vehicle-photos/DEMO-AR-001.jpg",
  "DEMO-SO-001": "/vehicle-photos/DEMO-SO-001.jpg",
  "DEMO-SO-002": "/vehicle-photos/DEMO-SO-002.jpg",
  "DEMO-SF-001": "/vehicle-photos/DEMO-SF-001.jpg",
  "DEMO-SF-002": "/vehicle-photos/DEMO-SF-002.jpg",
  "DEMO-HA-001": "/vehicle-photos/DEMO-HA-001.jpg",
  "DEMO-BI-001": "/vehicle-photos/DEMO-BI-001.jpg",
  "DEMO-NA-001": "/vehicle-photos/DEMO-NA-001.jpg",
  "DEMO-MO-001": "/vehicle-photos/DEMO-MO-001.jpg",
  "DEMO-TU-003": "/vehicle-photos/DEMO-TU-003.jpg",
  "DEMO-SO-003": "/vehicle-photos/DEMO-SO-003.jpg",
  "DEMO-TU-004": "/vehicle-photos/DEMO-TU-004.jpg"
}